{"timestamp": "Mon Mar 29 13:28:05 2021", "loosers": [{"ticker": "GSX", "name": "GSX Techedu Inc.", "change": "-41.56%"}, {"ticker": "DISCK", "name": "Discovery, Inc.", "change": "-29.55%"}, {"ticker": "DISCA", "name": "Discovery, Inc.", "change": "-27.45%"}, {"ticker": "VIAC", "name": "ViacomCBS Inc.", "change": "-27.31%"}, {"ticker": "VIACA", "name": "ViacomCBS Inc.", "change": "-25.60%"}, {"ticker": "SAIC", "name": "Science Applications International Corporation", "change": "-16.57%"}, {"ticker": "FUBO", "name": "fuboTV Inc.", "change": "-15.49%"}, {"ticker": "DAO", "name": "Youdao, Inc.", "change": "-13.72%"}, {"ticker": "DRTGF", "name": "Jet2 plc", "change": "-13.33%"}, {"ticker": "IBRX", "name": "ImmunityBio, Inc.", "change": "-13.31%"}, {"ticker": "IQ", "name": "iQIYI, Inc.", "change": "-13.20%"}, {"ticker": "TIGR", "name": "UP Fintech Holding Limited", "change": "-11.93%"}, {"ticker": "AMCX", "name": "AMC Networks Inc.", "change": "-11.27%"}, {"ticker": "EDU", "name": "New Oriental Education & Technology Group Inc.", "change": "-11.12%"}, {"ticker": "OLK", "name": "Olink Holding AB (publ)", "change": "-10.56%"}, {"ticker": "ITRO", "name": "Itronics Inc.", "change": "-10.40%"}, {"ticker": "MSGE", "name": "Madison Square Garden Entertainment Corp.", "change": "-9.87%"}, {"ticker": "FLGT", "name": "Fulgent Genetics, Inc.", "change": "-8.52%"}, {"ticker": "YY", "name": "JOYY Inc.", "change": "-8.43%"}, {"ticker": "FATE", "name": "Fate Therapeutics, Inc.", "change": "-8.10%"}, {"ticker": "DFIFF", "name": "Diamond Fields Resources Inc.", "change": "-7.76%"}, {"ticker": "TAL", "name": "TAL Education Group", "change": "-7.44%"}, {"ticker": "DM", "name": "Desktop Metal, Inc.", "change": "-6.99%"}, {"ticker": "ABCL", "name": "AbCellera Biologics Inc.", "change": "-6.88%"}, {"ticker": "SWAV", "name": "ShockWave Medical, Inc.", "change": "-6.42%"}]}