{"timestamp": "Mon Sep  6 13:23:44 2021", "loosers": [{"ticker": "GCPEF", "name": "GCL-Poly Energy Holdings Limited", "change": "-20.92%"}, {"ticker": "EGRNF", "name": "China Evergrande Group", "change": "-12.73%"}, {"ticker": "NGCRF", "name": "NagaCorp Ltd.", "change": "-12.48%"}, {"ticker": "AMRS", "name": "Amyris, Inc.", "change": "-7.87%"}, {"ticker": "CNM", "name": "Core & Main, Inc.", "change": "-7.71%"}, {"ticker": "SAVA", "name": "Cassava Sciences, Inc.", "change": "-7.64%"}, {"ticker": "BEKE", "name": "KE Holdings Inc.", "change": "-7.50%"}, {"ticker": "PTY", "name": "PIMCO Corporate & Income Opportunity Fund", "change": "-7.24%"}, {"ticker": "BKGFY", "name": "The Berkeley Group Holdings plc", "change": "-6.93%"}, {"ticker": "ADCT", "name": "ADC Therapeutics SA", "change": "-6.83%"}, {"ticker": "SPCE", "name": "Virgin Galactic Holdings, Inc.", "change": "-6.58%"}, {"ticker": "EDIT", "name": "Editas Medicine, Inc.", "change": "-6.43%"}, {"ticker": "CHJTF", "name": "CSPC Pharmaceutical Group Limited", "change": "-6.34%"}, {"ticker": "CRTX", "name": "Cortexyme, Inc.", "change": "-6.28%"}, {"ticker": "AFRM", "name": "Affirm Holdings, Inc.", "change": "-6.00%"}, {"ticker": "RLAY", "name": "Relay Therapeutics, Inc.", "change": "-5.91%"}, {"ticker": "OPK", "name": "OPKO Health, Inc.", "change": "-5.90%"}, {"ticker": "VCEL", "name": "Vericel Corporation", "change": "-5.64%"}, {"ticker": "ASND", "name": "Ascendis Pharma A/S", "change": "-5.61%"}, {"ticker": "TUYA", "name": "Tuya Inc.", "change": "-5.57%"}, {"ticker": "IBRX", "name": "ImmunityBio, Inc.", "change": "-5.44%"}, {"ticker": "YSG", "name": "Yatsen Holding Limited", "change": "-5.40%"}, {"ticker": "AAGH", "name": "America Great Health", "change": "-5.32%"}, {"ticker": "GME", "name": "GameStop Corp.", "change": "-5.04%"}, {"ticker": "IGMS", "name": "IGM Biosciences, Inc.", "change": "-5.04%"}]}