{"timestamp": "Tue Aug 17 15:19:50 2021", "loosers": [{"ticker": "SMFR", "name": "Sema4 Holdings Corp.", "change": "-15.98%"}, {"ticker": "VEDL", "name": "Vedanta Limited", "change": "-12.83%"}, {"ticker": "TME", "name": "Tencent Music Entertainment Group", "change": "-12.05%"}, {"ticker": "NPSNY", "name": "Naspers Limited", "change": "-10.16%"}, {"ticker": "SI", "name": "Silvergate Capital Corporation", "change": "-10.15%"}, {"ticker": "EGRNF", "name": "China Evergrande Group", "change": "-9.65%"}, {"ticker": "SAVA", "name": "Cassava Sciences, Inc.", "change": "-8.89%"}, {"ticker": "DXC", "name": "DXC Technology Company", "change": "-9.10%"}, {"ticker": "LYSDY", "name": "Lynas Rare Earths Limited", "change": "-9.98%"}, {"ticker": "HIPO", "name": "Hippo Holdings Inc.", "change": "-9.02%"}, {"ticker": "MVST", "name": "Microvast Holdings, Inc.", "change": "-8.89%"}, {"ticker": "BHP", "name": "BHP Group", "change": "-8.64%"}, {"ticker": "PLL", "name": "Piedmont Lithium Inc.", "change": "-9.07%"}, {"ticker": "LYSCF", "name": "Lynas Rare Earths Limited", "change": "-8.59%"}, {"ticker": "STVN", "name": "Stevanato Group S.p.A.", "change": "-8.56%"}, {"ticker": "WB", "name": "Weibo Corporation", "change": "-7.84%"}, {"ticker": "PILBF", "name": "Pilbara Minerals Limited", "change": "-8.09%"}, {"ticker": "BHPLF", "name": "BHP Group", "change": "-8.01%"}, {"ticker": "TDUP", "name": "ThredUp Inc.", "change": "-8.34%"}, {"ticker": "IBRX", "name": "ImmunityBio, Inc.", "change": "-7.66%"}, {"ticker": "ABCL", "name": "AbCellera Biologics Inc.", "change": "-7.87%"}, {"ticker": "LTHM", "name": "Livent Corporation", "change": "-7.37%"}, {"ticker": "IGT", "name": "International Game Technology PLC", "change": "-7.39%"}, {"ticker": "CELH", "name": "Celsius Holdings, Inc.", "change": "-7.25%"}, {"ticker": "MGNI", "name": "Magnite, Inc.", "change": "-6.93%"}]}