{"timestamp": "Thu Dec 17 17:32:22 2020", "loosers": [{"ticker": "PRRUF", "name": "Immutep Limited", "change": "-56.00%"}, {"ticker": "MLHR", "name": "Herman Miller, Inc.", "change": "-13.12%"}, {"ticker": "HZNP", "name": "Horizon Therapeutics Public Limited Company", "change": "-9.89%"}, {"ticker": "CVAC", "name": "CureVac N.V.", "change": "-6.86%"}, {"ticker": "SAUNF", "name": "AusNet Services Ltd", "change": "-7.14%"}, {"ticker": "NVTA", "name": "Invitae Corporation", "change": "-6.97%"}, {"ticker": "CHFFF", "name": "China Everbright Environment Group Limited", "change": "-6.14%"}, {"ticker": "VNE", "name": "Veoneer, Inc.", "change": "-5.71%"}, {"ticker": "YALA", "name": "Yalla Group Limited", "change": "-5.89%"}, {"ticker": "RCKT", "name": "Rocket Pharmaceuticals, Inc.", "change": "-5.25%"}, {"ticker": "PEB", "name": "Pebblebrook Hotel Trust", "change": "-5.16%"}, {"ticker": "IGMS", "name": "IGM Biosciences, Inc.", "change": "-4.53%"}, {"ticker": "PTVE", "name": "Pactiv Evergreen Inc.", "change": "-4.74%"}, {"ticker": "OZON", "name": "Ozon Holdings PLC", "change": "-4.25%"}, {"ticker": "XPEV", "name": "XPeng Inc.", "change": "-4.10%"}, {"ticker": "DM", "name": "Desktop Metal, Inc.", "change": "-3.85%"}, {"ticker": "TPTX", "name": "Turning Point Therapeutics, Inc.", "change": "-3.94%"}, {"ticker": "HCACW", "name": "Hennessy Capital Acquisition Corp. IV", "change": "-3.92%"}, {"ticker": "ALGM", "name": "Allegro MicroSystems, Inc.", "change": "-3.77%"}, {"ticker": "SGIOY", "name": "Shionogi & Co., Ltd.", "change": "-3.80%"}, {"ticker": "IQ", "name": "iQIYI, Inc.", "change": "-3.65%"}, {"ticker": "GRWG", "name": "GrowGeneration Corp.", "change": "-3.73%"}, {"ticker": "ETRN", "name": "Equitrans Midstream Corporation", "change": "-3.62%"}, {"ticker": "BNR", "name": "Burning Rock Biotech Limited", "change": "-3.64%"}, {"ticker": "ACOPF", "name": "The a2 Milk Company Limited", "change": "-3.62%"}]}