{"timestamp": "Fri Dec 18 18:25:40 2020", "loosers": [{"ticker": "WNW", "name": "Wunong Net Technology Company Limited", "change": "-35.76%"}, {"ticker": "NWARF", "name": "Norwegian Air Shuttle ASA", "change": "-21.88%"}, {"ticker": "ACOPF", "name": "The a2 Milk Company Limited", "change": "-16.97%"}, {"ticker": "BKFCF", "name": "Bank of Communications Co., Ltd.", "change": "-15.09%"}, {"ticker": "PRRUF", "name": "Immutep Limited", "change": "-13.95%"}, {"ticker": "BB", "name": "BlackBerry Limited", "change": "-13.44%"}, {"ticker": "OTGLY", "name": "CD Projekt S.A.", "change": "-13.48%"}, {"ticker": "QBIEY", "name": "QBE Insurance Group Limited", "change": "-13.00%"}, {"ticker": "ALVR", "name": "AlloVir, Inc.", "change": "-8.58%"}, {"ticker": "YQ", "name": "17 Education & Technology Group Inc.", "change": "-7.71%"}, {"ticker": "AFTPY", "name": "Afterpay Limited", "change": "-7.25%"}, {"ticker": "CDE", "name": "Coeur Mining, Inc.", "change": "-7.12%"}, {"ticker": "MEDP", "name": "Medpace Holdings, Inc.", "change": "-6.67%"}, {"ticker": "OSTK", "name": "Overstock.com, Inc.", "change": "-6.53%"}, {"ticker": "NNOX", "name": "Nano-X Imaging Ltd.", "change": "-6.56%"}, {"ticker": "X", "name": "United States Steel Corporation", "change": "-6.06%"}, {"ticker": "SWI", "name": "SolarWinds Corporation", "change": "-5.91%"}, {"ticker": "FDX", "name": "FedEx Corporation", "change": "-5.26%"}, {"ticker": "HYLN", "name": "Hyliion Holdings Corp.", "change": "-4.90%"}, {"ticker": "DORM", "name": "Dorman Products, Inc.", "change": "-4.95%"}, {"ticker": "CVAC", "name": "CureVac N.V.", "change": "-4.95%"}, {"ticker": "SMICY", "name": "Semiconductor Manufacturing International Corporation", "change": "-4.80%"}, {"ticker": "NVCR", "name": "NovoCure Limited", "change": "-4.74%"}, {"ticker": "NKTR", "name": "Nektar Therapeutics", "change": "-4.47%"}, {"ticker": "MAKSY", "name": "Marks and Spencer Group plc", "change": "-4.43%"}]}