{"timestamp": "Mon Feb  8 19:13:07 2021", "loosers": [{"ticker": "AMC", "name": "AMC Entertainment Holdings, Inc.", "change": "-11.64%"}, {"ticker": "CRNC", "name": "Cerence Inc.", "change": "-10.93%"}, {"ticker": "HUYA", "name": "HUYA Inc.", "change": "-9.08%"}, {"ticker": "RLX", "name": "RLX Technology Inc.", "change": "-8.19%"}, {"ticker": "HYMTF", "name": "Hyundai Motor Company", "change": "-8.03%"}, {"ticker": "PENN", "name": "Penn National Gaming, Inc.", "change": "-7.21%"}, {"ticker": "GME", "name": "GameStop Corp.", "change": "-7.34%"}, {"ticker": "MKSI", "name": "MKS Instruments, Inc.", "change": "-7.09%"}, {"ticker": "SGEN", "name": "Seagen Inc.", "change": "-6.64%"}, {"ticker": "CCIV", "name": "Churchill Capital Corp IV", "change": "-6.75%"}, {"ticker": "APPN", "name": "Appian Corporation", "change": "-6.53%"}, {"ticker": "CPYYF", "name": "Centrica plc", "change": "-6.16%"}, {"ticker": "NWAU", "name": "Consumer Automotive Finance, Inc.", "change": "-6.02%"}, {"ticker": "PUBM", "name": "PubMatic, Inc.", "change": "-5.91%"}, {"ticker": "HKIB", "name": "AMTD International Inc.", "change": "-5.67%"}, {"ticker": "YSG", "name": "Yatsen Holding Limited", "change": "-5.49%"}, {"ticker": "CLOV", "name": "Clover Health Investments, Corp.", "change": "-5.14%"}, {"ticker": "DNB", "name": "Dun & Bradstreet Holdings, Inc.", "change": "-5.30%"}, {"ticker": "VRNS", "name": "Varonis Systems, Inc.", "change": "-5.18%"}, {"ticker": "DFIFF", "name": "Diamond Fields Resources Inc.", "change": "-5.26%"}, {"ticker": "PBR", "name": "Petr\u00f3leo Brasileiro S.A. - Petrobras", "change": "-5.24%"}, {"ticker": "ARCE", "name": "Arco Platform Limited", "change": "-5.34%"}, {"ticker": "DOYU", "name": "DouYu International Holdings Limited", "change": "-5.00%"}, {"ticker": "MOMO", "name": "Momo Inc.", "change": "-4.95%"}, {"ticker": "COLM", "name": "Columbia Sportswear Company", "change": "-4.85%"}]}