{"timestamp": "Tue Dec 22 18:30:12 2020", "loosers": [{"ticker": "KNSL", "name": "Kinsale Capital Group, Inc.", "change": "-11.10%"}, {"ticker": "CMCLF", "name": "China Molybdenum Co., Ltd.", "change": "-9.63%"}, {"ticker": "MRNA", "name": "Moderna, Inc.", "change": "-9.44%"}, {"ticker": "PHJMF", "name": "PT Hanjaya Mandala Sampoerna Tbk", "change": "-9.17%"}, {"ticker": "NVAX", "name": "Novavax, Inc.", "change": "-9.04%"}, {"ticker": "BJCHF", "name": "Beijing Capital International Airport Company Limited", "change": "-8.24%"}, {"ticker": "GCPEF", "name": "GCL-Poly Energy Holdings Limited", "change": "-7.89%"}, {"ticker": "KMX", "name": "CarMax, Inc.", "change": "-7.49%"}, {"ticker": "OSTK", "name": "Overstock.com, Inc.", "change": "-7.22%"}, {"ticker": "BNTX", "name": "BioNTech SE", "change": "-7.00%"}, {"ticker": "KC", "name": "Kingsoft Cloud Holdings Limited", "change": "-5.61%"}, {"ticker": "HUYA", "name": "HUYA Inc.", "change": "-6.68%"}, {"ticker": "CYDY", "name": "CytoDyn Inc.", "change": "-6.00%"}, {"ticker": "NCLH", "name": "Norwegian Cruise Line Holdings Ltd.", "change": "-5.91%"}, {"ticker": "SSL", "name": "Sasol Limited", "change": "-5.84%"}, {"ticker": "LU", "name": "Lufax Holding Ltd", "change": "-5.63%"}, {"ticker": "AG", "name": "First Majestic Silver Corp.", "change": "-5.67%"}, {"ticker": "CICHF", "name": "China Construction Bank Corporation", "change": "-5.48%"}, {"ticker": "LI", "name": "Li Auto Inc.", "change": "-5.08%"}, {"ticker": "KEP", "name": "Korea Electric Power Corporation", "change": "-5.13%"}, {"ticker": "MOS", "name": "The Mosaic Company", "change": "-5.21%"}, {"ticker": "ACH", "name": "Aluminum Corporation of China Limited", "change": "-5.14%"}, {"ticker": "SUMO", "name": "Sumo Logic, Inc.", "change": "-5.21%"}, {"ticker": "XPEV", "name": "XPeng Inc.", "change": "-5.37%"}, {"ticker": "BYDDY", "name": "BYD Company Limited", "change": "-4.84%"}]}