{"timestamp": "Tue Jun 29 16:27:56 2021", "loosers": [{"ticker": "VCEL", "name": "Vericel Corporation", "change": "-12.77%"}, {"ticker": "SPCE", "name": "Virgin Galactic Holdings, Inc.", "change": "-11.03%"}, {"ticker": "KRTX", "name": "Karuna Therapeutics, Inc.", "change": "-8.75%"}, {"ticker": "BABWF", "name": "International Consolidated Airlines Group, S.A.", "change": "-8.08%"}, {"ticker": "LX", "name": "LexinFintech Holdings Ltd.", "change": "-7.79%"}, {"ticker": "YSHLF", "name": "Yangzijiang Shipbuilding (Holdings) Ltd.", "change": "-6.66%"}, {"ticker": "IOVA", "name": "Iovance Biotherapeutics, Inc.", "change": "-6.57%"}, {"ticker": "ALMMF", "name": "Aluminum Corporation of China Limited", "change": "-6.36%"}, {"ticker": "MLHR", "name": "Herman Miller, Inc.", "change": "-6.26%"}, {"ticker": "EH", "name": "EHang Holdings Limited", "change": "-5.21%"}, {"ticker": "FIGS", "name": "FIGS, Inc.", "change": "-5.02%"}, {"ticker": "SQSP", "name": "Squarespace, Inc.", "change": "-5.00%"}, {"ticker": "MRTX", "name": "Mirati Therapeutics, Inc.", "change": "-4.84%"}, {"ticker": "GSAT", "name": "Globalstar, Inc.", "change": "-4.81%"}, {"ticker": "RLX", "name": "RLX Technology Inc.", "change": "-4.82%"}, {"ticker": "TIL", "name": "Instil Bio, Inc.", "change": "-4.82%"}, {"ticker": "BDRAF", "name": "Bombardier Inc.", "change": "-4.69%"}, {"ticker": "NOKPF", "name": "Nok Airlines Public Company Limited", "change": "-3.11%"}, {"ticker": "RLLCF", "name": "Rolls-Royce Holdings plc", "change": "-4.89%"}, {"ticker": "AUOTY", "name": "AU Optronics Corp.", "change": "-4.47%"}, {"ticker": "YSG", "name": "Yatsen Holding Limited", "change": "-4.55%"}, {"ticker": "PILBF", "name": "Pilbara Minerals Limited", "change": "-4.42%"}, {"ticker": "BE", "name": "Bloom Energy Corporation", "change": "-4.44%"}, {"ticker": "FTCH", "name": "Farfetch Limited", "change": "-4.42%"}, {"ticker": "W", "name": "Wayfair Inc.", "change": "-4.16%"}]}