{"timestamp": "Fri Dec 18 16:33:40 2020", "loosers": [{"ticker": "WNW", "name": "Wunong Net Technology Company Limited", "change": "-33.70%"}, {"ticker": "PRRUF", "name": "Immutep Limited", "change": "-25.35%"}, {"ticker": "NWARF", "name": "Norwegian Air Shuttle ASA", "change": "-23.50%"}, {"ticker": "ACOPF", "name": "The a2 Milk Company Limited", "change": "-17.28%"}, {"ticker": "BKFCF", "name": "Bank of Communications Co., Ltd.", "change": "-15.09%"}, {"ticker": "OTGLY", "name": "CD Projekt S.A.", "change": "-13.82%"}, {"ticker": "BB", "name": "BlackBerry Limited", "change": "-13.26%"}, {"ticker": "CDE", "name": "Coeur Mining, Inc.", "change": "-8.10%"}, {"ticker": "AFTPY", "name": "Afterpay Limited", "change": "-7.25%"}, {"ticker": "MEDP", "name": "Medpace Holdings, Inc.", "change": "-6.10%"}, {"ticker": "OSTK", "name": "Overstock.com, Inc.", "change": "-5.95%"}, {"ticker": "FDX", "name": "FedEx Corporation", "change": "-5.55%"}, {"ticker": "ARCT", "name": "Arcturus Therapeutics Holdings Inc.", "change": "-5.65%"}, {"ticker": "X", "name": "United States Steel Corporation", "change": "-4.95%"}, {"ticker": "SMICY", "name": "Semiconductor Manufacturing International Corporation", "change": "-4.80%"}, {"ticker": "CODYY", "name": "Compagnie de Saint-Gobain S.A.", "change": "-4.50%"}, {"ticker": "MAKSY", "name": "Marks and Spencer Group plc", "change": "-4.43%"}, {"ticker": "HYLN", "name": "Hyliion Holdings Corp.", "change": "-4.65%"}, {"ticker": "DORM", "name": "Dorman Products, Inc.", "change": "-4.95%"}, {"ticker": "NNOX", "name": "Nano-X Imaging Ltd.", "change": "-3.48%"}, {"ticker": "DKILY", "name": "Daikin Industries,Ltd.", "change": "-3.79%"}, {"ticker": "BIGC", "name": "BigCommerce Holdings, Inc.", "change": "-4.13%"}, {"ticker": "AMADY", "name": "Amadeus IT Group, S.A.", "change": "-4.07%"}, {"ticker": "SBRCY", "name": "Sberbank of Russia", "change": "-4.03%"}, {"ticker": "LYG", "name": "Lloyds Banking Group plc", "change": "-3.91%"}]}