{"timestamp": "Wed Apr  7 18:37:21 2021", "loosers": [{"ticker": "UPST", "name": "Upstart Holdings, Inc.", "change": "-12.32%"}, {"ticker": "MARA", "name": "Marathon Digital Holdings, Inc.", "change": "-11.71%"}, {"ticker": "LI", "name": "Li Auto Inc.", "change": "-11.14%"}, {"ticker": "YSG", "name": "Yatsen Holding Limited", "change": "-10.91%"}, {"ticker": "RIOT", "name": "Riot Blockchain, Inc.", "change": "-10.46%"}, {"ticker": "VYGVF", "name": "Voyager Digital Ltd.", "change": "-9.62%"}, {"ticker": "BFAM", "name": "Bright Horizons Family Solutions Inc.", "change": "-9.36%"}, {"ticker": "AAGH", "name": "America Great Health", "change": "-8.63%"}, {"ticker": "SPWR", "name": "SunPower Corporation", "change": "-8.44%"}, {"ticker": "PLUG", "name": "Plug Power Inc.", "change": "-8.21%"}, {"ticker": "FLGT", "name": "Fulgent Genetics, Inc.", "change": "-8.11%"}, {"ticker": "LAZR", "name": "Luminar Technologies, Inc.", "change": "-8.04%"}, {"ticker": "NTLA", "name": "Intellia Therapeutics, Inc.", "change": "-8.19%"}, {"ticker": "OM", "name": "Outset Medical, Inc.", "change": "-8.05%"}, {"ticker": "SI", "name": "Silvergate Capital Corporation", "change": "-8.07%"}, {"ticker": "AI", "name": "C3.ai, Inc.", "change": "-7.88%"}, {"ticker": "TCEHY", "name": "Tencent Holdings Limited", "change": "-7.60%"}, {"ticker": "ALHC", "name": "Alignment Healthcare Holdings, LLC", "change": "-7.38%"}, {"ticker": "TCTZF", "name": "Tencent Holdings Limited", "change": "-6.93%"}, {"ticker": "TIGR", "name": "UP Fintech Holding Limited", "change": "-7.88%"}, {"ticker": "MSTR", "name": "MicroStrategy Incorporated", "change": "-7.30%"}, {"ticker": "SHLS", "name": "Shoals Technologies Group, Inc.", "change": "-7.48%"}, {"ticker": "CHPT", "name": "Chargepoint Holdings Inc.", "change": "-7.66%"}, {"ticker": "FCEL", "name": "FuelCell Energy, Inc.", "change": "-7.36%"}, {"ticker": "KRNT", "name": "Kornit Digital Ltd.", "change": "-7.19%"}]}