{"timestamp": "Thu May 13 19:24:59 2021", "loosers": [{"ticker": "WISH", "name": "ContextLogic Inc.", "change": "-29.82%"}, {"ticker": "POSH", "name": "Poshmark, Inc.", "change": "-22.22%"}, {"ticker": "AMWL", "name": "American Well Corporation", "change": "-21.65%"}, {"ticker": "FLR", "name": "Fluor Corporation", "change": "-19.87%"}, {"ticker": "TRQ", "name": "Turquoise Hill Resources Ltd.", "change": "-18.28%"}, {"ticker": "BFLY", "name": "Butterfly Network, Inc.", "change": "-16.47%"}, {"ticker": "ONEM", "name": "1Life Healthcare, Inc.", "change": "-14.98%"}, {"ticker": "BMBL", "name": "Bumble Inc.", "change": "-14.46%"}, {"ticker": "HAE", "name": "Haemonetics Corporation", "change": "-13.78%"}, {"ticker": "PAAS", "name": "Pan American Silver Corp.", "change": "-11.14%"}, {"ticker": "DQ", "name": "Daqo New Energy Corp.", "change": "-10.96%"}, {"ticker": "SHLS", "name": "Shoals Technologies Group, Inc.", "change": "-10.48%"}, {"ticker": "CPNG", "name": "Coupang, Inc.", "change": "-10.19%"}, {"ticker": "MSTR", "name": "MicroStrategy Incorporated", "change": "-9.87%"}, {"ticker": "OSCR", "name": "Oscar Health, Inc.", "change": "-10.34%"}, {"ticker": "OLO", "name": "Olo Inc.", "change": "-10.16%"}, {"ticker": "SHC", "name": "Sotera Health Company", "change": "-10.13%"}, {"ticker": "TAL", "name": "TAL Education Group", "change": "-9.93%"}, {"ticker": "UPST", "name": "Upstart Holdings, Inc.", "change": "-9.87%"}, {"ticker": "VYGVF", "name": "Voyager Digital Ltd.", "change": "-9.36%"}, {"ticker": "DOYU", "name": "DouYu International Holdings Limited", "change": "-9.20%"}, {"ticker": "DAO", "name": "Youdao, Inc.", "change": "-9.27%"}, {"ticker": "NEXOY", "name": "NEXON Co., Ltd.", "change": "-9.14%"}, {"ticker": "KC", "name": "Kingsoft Cloud Holdings Limited", "change": "-8.45%"}, {"ticker": "RBLX", "name": "Roblox Corporation", "change": "-8.29%"}]}