{"timestamp": "Fri Jan 15 14:44:54 2021", "loosers": [{"ticker": "BPRMF", "name": "Blue Prism Group plc", "change": "-14.06%"}, {"ticker": "XIACF", "name": "Xiaomi Corporation", "change": "-9.35%"}, {"ticker": "EAF", "name": "GrafTech International Ltd.", "change": "-8.40%"}, {"ticker": "XIACY", "name": "Xiaomi Corporation", "change": "-7.54%"}, {"ticker": "BLDP", "name": "Ballard Power Systems Inc.", "change": "-8.41%"}, {"ticker": "WISH", "name": "ContextLogic Inc.", "change": "-7.70%"}, {"ticker": "TNABY", "name": "Tenaga Nasional Berhad", "change": "-7.19%"}, {"ticker": "ATRC", "name": "AtriCure, Inc.", "change": "-6.91%"}, {"ticker": "GWLLF", "name": "Great Wall Motor Company Limited", "change": "-6.87%"}, {"ticker": "DDD", "name": "3D Systems Corporation", "change": "-5.75%"}, {"ticker": "AVAV", "name": "AeroVironment, Inc.", "change": "-7.13%"}, {"ticker": "PLUG", "name": "Plug Power Inc.", "change": "-7.08%"}, {"ticker": "TTNDY", "name": "Techtronic Industries Company Limited", "change": "-5.93%"}, {"ticker": "HL", "name": "Hecla Mining Company", "change": "-6.07%"}, {"ticker": "PRGS", "name": "Progress Software Corporation", "change": "-5.74%"}, {"ticker": "FCEL", "name": "FuelCell Energy, Inc.", "change": "-8.07%"}, {"ticker": "MCARY", "name": "Mercari, Inc.", "change": "-5.66%"}, {"ticker": "SID", "name": "Companhia Sider\u00fargica Nacional", "change": "-5.45%"}, {"ticker": "TGLVY", "name": "Top Glove Corporation Bhd.", "change": "-5.55%"}, {"ticker": "SEDG", "name": "SolarEdge Technologies, Inc.", "change": "-6.14%"}, {"ticker": "GNENF", "name": "Ganfeng Lithium Co., Ltd.", "change": "-5.43%"}, {"ticker": "AA", "name": "Alcoa Corporation", "change": "-4.98%"}, {"ticker": "MSTR", "name": "MicroStrategy Incorporated", "change": "-5.00%"}, {"ticker": "LMND", "name": "Lemonade, Inc.", "change": "-4.03%"}, {"ticker": "TPIC", "name": "TPI Composites, Inc.", "change": "-5.17%"}]}