{"timestamp": "Wed Mar  3 20:19:26 2021", "loosers": [{"ticker": "RKT", "name": "Rocket Companies, Inc.", "change": "-32.42%"}, {"ticker": "VIR", "name": "Vir Biotechnology, Inc.", "change": "-23.77%"}, {"ticker": "FUBO", "name": "fuboTV Inc.", "change": "-18.48%"}, {"ticker": "DSP", "name": "Viant Technology Inc.", "change": "-17.99%"}, {"ticker": "DFIFF", "name": "Diamond Fields Resources Inc.", "change": "-15.47%"}, {"ticker": "PUBM", "name": "PubMatic, Inc.", "change": "-14.94%"}, {"ticker": "FSR", "name": "Fisker Inc.", "change": "-14.57%"}, {"ticker": "ZI", "name": "ZoomInfo Technologies Inc.", "change": "-14.31%"}, {"ticker": "TSNPD", "name": "HUMBL, Inc.", "change": "-13.33%"}, {"ticker": "SANA", "name": "Sana Biotechnology, Inc.", "change": "-12.99%"}, {"ticker": "PTAIF", "name": "PT Astra International Tbk", "change": "-13.14%"}, {"ticker": "EXPI", "name": "eXp World Holdings, Inc.", "change": "-12.94%"}, {"ticker": "FVRR", "name": "Fiverr International Ltd.", "change": "-12.26%"}, {"ticker": "DQ", "name": "Daqo New Energy Corp.", "change": "-12.30%"}, {"ticker": "GSX", "name": "GSX Techedu Inc.", "change": "-12.09%"}, {"ticker": "DNMR", "name": "Danimer Scientific, Inc.", "change": "-12.21%"}, {"ticker": "TTD", "name": "The Trade Desk, Inc.", "change": "-12.03%"}, {"ticker": "QTRX", "name": "Quanterix Corporation", "change": "-11.74%"}, {"ticker": "MGNI", "name": "Magnite, Inc.", "change": "-11.34%"}, {"ticker": "MKTX", "name": "MarketAxess Holdings Inc.", "change": "-11.56%"}, {"ticker": "ETSY", "name": "Etsy, Inc.", "change": "-11.15%"}, {"ticker": "RUN", "name": "Sunrun Inc.", "change": "-11.02%"}, {"ticker": "NOVA", "name": "Sunnova Energy International Inc.", "change": "-10.81%"}, {"ticker": "BAND", "name": "Bandwidth Inc.", "change": "-11.02%"}, {"ticker": "FDVRF", "name": "Facedrive Inc.", "change": "-11.42%"}]}